.travis.yml
MANIFEST.in
README.md
setup.cfg
setup.py
pyscarab.egg-info/PKG-INFO
pyscarab.egg-info/SOURCES.txt
pyscarab.egg-info/dependency_links.txt
pyscarab.egg-info/top_level.txt
scarab/__init__.py
scarab/loader.py
scarab/main.py
scarab/predefs.py
scarab/types.py
scarab/tests/__init__.py
scarab/tests/test_scarab.py