Metadata-Version: 1.1
Name: pyscarab
Version: 0.1
Summary: Python bindings for libscarab
Home-page: https://github.com/blindstore/pyscarab
Author: Bogdan Kulynych, Benjamin Lipp, Davide Kirchner
Author-email: hello@hidden-markov.com, mail@benjaminlipp.de, davide.kirchner@yahoo.it
License: MIT
Keywords: crypto
Platform: UNKNOWN
Classifier: Development Status :: 3 - Alpha
Classifier: Intended Audience :: Developers
Classifier: Topic :: Security :: Cryptography
Classifier: License :: OSI Approved :: MIT License
Classifier: Programming Language :: Python :: 2.7
Classifier: Programming Language :: Python :: 3.4
